LICENSE
README.md
setup.cfg
setup.py
pytecord/__init__.py
pytecord/annotations.py
pytecord/app.py
pytecord/channel.py
pytecord/client.py
pytecord/connection.py
pytecord/enums.py
pytecord/files.py
pytecord/hook.py
pytecord/listener.py
pytecord/payloads.py
pytecord/profiles.py
pytecord/role.py
pytecord/route.py
pytecord/ui.py
pytecord/utils.py
pytecord.egg-info/PKG-INFO
pytecord.egg-info/SOURCES.txt
pytecord.egg-info/dependency_links.txt
pytecord.egg-info/not-zip-safe
pytecord.egg-info/requires.txt
pytecord.egg-info/top_level.txt