Metadata-Version: 2.1
Name: pytecord
Version: 1.0a1
Summary: Pytecord - library for creating bots in discord written in Python
Home-page: https://github.com/pixeldeee/pytecord
Download-URL: https://github.com/pixeldeee/pytecord/releases/tag/1.0-alpha-1
Author: pixeldeee
Author-email: aitiiigg1@gmail.com
Classifier: Programming Language :: Python :: 3
Classifier: Programming Language :: Python :: 3.11
Requires-Python: >=3.11
License-File: LICENSE
